setup.py
arkadip_dsnd_distributions.egg-info/PKG-INFO
arkadip_dsnd_distributions.egg-info/SOURCES.txt
arkadip_dsnd_distributions.egg-info/dependency_links.txt
arkadip_dsnd_distributions.egg-info/not-zip-safe
arkadip_dsnd_distributions.egg-info/top_level.txt
distributions/Binomialdistribution.py
distributions/Gaussiandistribution.py
distributions/Generaldistribution.py
distributions/__init__.py