Metadata-Version: 1.0
Name: arkadip-dsnd-distributions
Version: 0.1
Summary: Arkadip"s Gaussian distributions
Home-page: UNKNOWN
Author: UNKNOWN
Author-email: UNKNOWN
License: UNKNOWN
Platform: UNKNOWN
